dicon/__init__.py
dicon/dicon.py
dicon/util.py
dicon-0.0.3.dist-info/METADATA
dicon-0.0.3.dist-info/RECORD
dicon-0.0.3.dist-info/WHEEL
dicon-0.0.3.dist-info/top_level.txt
