Metadata-Version: 2.1
Name: dicon
Version: 0.0.3
Summary: Dicon, simple DI container injection liblary for Python.
Home-page: https://github.com/kenoss/dicon
Author: keno
Author-email: keno.ss57@gmail.com
License: MIT
Platform: UNKNOWN
Classifier: Development Status :: 2 - Pre-Alpha
Classifier: License :: OSI Approved :: MIT License
Classifier: Topic :: Utilities
Classifier: Programming Language :: Python :: 3.5
Classifier: Programming Language :: Python :: 3.6
Classifier: Programming Language :: Python :: 3 :: Only
